{"type": "Feature", "id": 12513376, "properties": {"woe:id": 12513376, "woe:parent_id": 849141, "woe:name": "Zagreb Airport", "woe:placetype": 14, "woe:placetype_name": "Airport", "woe:lang": "ENG", "iso:country": "HR", "meta:provider": ["geoplanet:7.3.1", "geoplanet:7.3.2", "geoplanet:7.4.0", "geoplanet:7.4.1", "geoplanet:7.5.1", "geoplanet:7.5.2", "geoplanet:7.6.0", "geoplanet:7.8.1", "geoplanet:7.9.0", "geoplanet:7.10.0", "geoplanet:8.0.0", "woeplanet:8.0.0"], "meta:indexed": "2020-08-20T20:27:32.820635", "woe:alias_FIN_V": ["Zagrebin Lentokentt\u00e4", "Zagrebin Lentokentta"], "woe:alias_ENG_V": ["Zracna Luka Zagreb", "ZAG", "ZAG Airport"], "woe:alias_ITA_V": ["Aeroporto Di Zagabria"], "woe:alias_DAN_V": ["Zagreb Lufthavn"], "woe:alias_UNK_V": ["Letiste Zahreb", "Letisko Zahreb"], "woe:alias_DUT_V": ["Vliegveld Zagreb"], "woe:alias_POR_V": ["Aeroporto de Zagreb"], "woe:alias_SWE_V": ["Zagreb Flygplats"], "meta:updated": "2020-08-22T02:50:49.784470", "woe:alias_GER_V": ["Flughafen Zagreb"], "woe:alias_FRE_V": ["Aeroport de Zagreb", "A\u00e9roport de Zagreb"], "woe:alias_SPA_V": ["Aeropuerto de Zagreb"], "woe:hierarchy": {"continent": 24865675, "country": 23424843, "town": 0, "planet": 1, "county": 15022255, "suburb": 0, "state": 12577990, "region": 0, "localadmin": 0}, "woe:timezone_id": 28350889, "woe:hash": "u25kjmnxnzjt", "woe:centroid": [16.060249, 45.731831], "geom:latitude": 45.731831, "geom:longitude": 16.060249, "geom:hash": "u25kjmnxnzjt", "woe:latitude": 45.731831, "geom:centroid": [16.060249, 45.731831], "woe:longitude": 16.060249, "woe:repo": "woeplanet-airport-hr"}, "geometry": {"coordinates": [16.060249, 45.731831], "type": "Point"}}